{
  "xTitle": "Ebert - Conroy",
  "yTitle": "Capacity Utilization",
  "labels": [
    "Ebert - Conroy"
  ],
  "datasets": [
    {
      "label": "Gulgowski - Wilkinson",
      "data": [
        34894.37
      ],
      "stack": "stack 0"
    },
    {
      "label": "Sipes and Sons",
      "data": [
        11910.97
      ],
      "stack": "stack 0"
    },
    {
      "label": "Robel and Sons",
      "data": [
        19387.3
      ],
      "stack": "stack 0"
    },
    {
      "label": "Rippin Inc",
      "data": [
        16522.15
      ],
      "stack": "stack 0"
    },
    {
      "label": "Frami, Sawayn and Connelly",
      "data": [
        18304.34
      ],
      "stack": "stack 0"
    },
    {
      "label": "Cummerata and Sons",
      "data": [
        18415.28
      ],
      "stack": "stack 0"
    },
    {
      "label": "Unutilized Capacity",
      "data": [
        31494.2
      ],
      "stack": "stack 0"
    }
  ]
}